litegrad/__init__.py
litegrad/main.py
litegrad-0.0.1.dist-info/METADATA
litegrad-0.0.1.dist-info/WHEEL
litegrad-0.0.1.dist-info/licenses/LICENSE
litegrad-0.0.1.dist-info/RECORD
