Metadata-Version: 2.4
Name: litegrad
Version: 0.0.1
Summary: A minimal implementation of PyTorch's autograd engine
Author-email: Miguel Barbosa Pereira <miguel.b.per@gmail.com>
License-File: LICENSE
Requires-Python: >=3.9
Requires-Dist: numpy>=2.0.0
